buelon/__init__.py
buelon/bucket.py
buelon/bucket_v1.py
buelon/command_line.py
buelon/command_line_v1.py
buelon/hub.py
buelon/hub_v1.py
buelon/hub_v2.py
buelon/og_web.py
buelon/settings.py
buelon/web.py
buelon/worker.py
buelon/worker_v1.py
buelon/worker_v2.py
buelon/core/__init__.py
buelon/core/action.py
buelon/core/execution.py
buelon/core/loop.py
buelon/core/pipe.py
buelon/core/pipe_debug.py
buelon/core/pipe_interpreter.py
buelon/core/step.py
buelon/core/step_definition.py
buelon/cython/c_bucket.pyx
buelon/cython/c_hub.pyx
buelon/cython/c_worker.pyx
buelon/examples/__init__.py
buelon/examples/demo.py
buelon/examples/example.bue
buelon/examples/example.py
buelon/helpers/__init__.py
buelon/helpers/created_cache.py
buelon/helpers/json_parser.py
buelon/helpers/lazy_load_class.py
buelon/helpers/persistqueue.py
buelon/helpers/pipe_util.py
buelon/helpers/postgres.py
buelon/helpers/sqlite3_helper.py
buelon/jokes/__init__.py
buelon/jokes/jokes.py
buelon-1.0.74.dist-info/licenses/LICENSE
buelon-1.0.74.dist-info/METADATA
buelon-1.0.74.dist-info/WHEEL
buelon-1.0.74.dist-info/entry_points.txt
buelon-1.0.74.dist-info/top_level.txt
buelon-1.0.74.dist-info/RECORD
