Metadata-Version: 2.4
Name: buelon
Version: 1.0.74
Summary: A scripting language to simply manage a very large amount of i/o heavy workloads. Such as API calls for your ETL, ELT or any program needing Python and/or SQL
Home-page: https://github.com/daniel-olson-code/buelon
Author: Daniel Olson
Author-email: daniel@orphos.cloud
Keywords: buelon etl pipeline asynchronous data-processing api
Classifier: Development Status :: 3 - Alpha
Classifier: Intended Audience :: Developers
Classifier: License :: OSI Approved :: MIT License
Classifier: Operating System :: OS Independent
Classifier: Programming Language :: Python :: 3
Classifier: Programming Language :: Python :: 3.10
Classifier: Programming Language :: Python :: 3.11
Classifier: Programming Language :: Python :: 3.12
Requires-Python: >=3.10
License-File: LICENSE
Requires-Dist: Cython
Requires-Dist: psycopg2-binary
Requires-Dist: orjson
Requires-Dist: python-dotenv
Requires-Dist: asyncio-pool
Requires-Dist: psutil
Requires-Dist: unsync
Requires-Dist: redis
Requires-Dist: persistqueue
Requires-Dist: PyYAML
Requires-Dist: kazoo
Requires-Dist: tqdm
Requires-Dist: asyncpg
Requires-Dist: websockets
Requires-Dist: fastapi
Requires-Dist: uvicorn
Requires-Dist: bisocket
Dynamic: author
Dynamic: author-email
Dynamic: classifier
Dynamic: description
Dynamic: description-content-type
Dynamic: home-page
Dynamic: keywords
Dynamic: license-file
Dynamic: requires-dist
Dynamic: requires-python
Dynamic: summary
